INSTALL.txt
LICENSE.txt
MANIFEST.in
README.rst
ez_setup.py
setup.py
django_reusableapps.egg-info/PKG-INFO
django_reusableapps.egg-info/SOURCES.txt
django_reusableapps.egg-info/dependency_links.txt
django_reusableapps.egg-info/top_level.txt
docs/overview.rst
docs/setup-example.py
reusableapps/__init__.py