Metadata-Version: 1.0
Name: django-reusableapps
Version: 0.1.1
Summary: Reusable Django apps with setuptools
Home-page: http://code.google.com/p/django-reusableapps/
Author: Jannis Leidel
Author-email: jannis@leidel.info
License: UNKNOWN
Platform: UNKNOWN
Classifier: Development Status :: 4 - Beta
Classifier: Environment :: Web Environment
Classifier: Intended Audience :: Developers
Classifier: License :: OSI Approved :: BSD License
Classifier: Operating System :: OS Independent
Classifier: Programming Language :: Python
Classifier: Topic :: Utilities
